[
  {
    "title": "Honda Accord LX",
    "price": 22000,
    "description": "A stylish Honda Accord with advanced features.",
    "stockNo": 987654,
    "vinNo": "XYZ987654321",
    "chassisNo": "ABC123456789",
    "numberPlate": "XYZ-987",
    "make": "Honda",
    "model": "Accord",
    "year": 2019,
    "kilometers": 30000,
    "body": "Sedan",
    "transmission": "Automatic",
    "doors": 4,
    "seats": 5,
    "color": "White",
    "fuelType": "Petrol",
    "engineSize": "2.4L",
    "wofExpire": "2024-02-28T00:00:00.000Z",
    "regoExpire": "2024-03-15T00:00:00.000Z",
    "numberOfOwners": 1,
    "cylinders": 4,
    "images": [
      {
        "public_id": "honda-accord-image1",
        "url": "https://images.unsplash.com/photo-1580273916550-e323be2ae537?ixlib=rb-4.0.3&ixid=M3wxMjA3fDB8MHxwaG90by1wYWdlfHx8fGVufDB8fHx8fA%3D%3D&auto=format&fit=crop&w=464&q=80"
      },
      {
        "public_id": "honda-accord-image2",
        "url": "https://images.unsplash.com/photo-1498887960847-2a5e46312788?ixlib=rb-4.0.3&ixid=M3wxMjA3fDB8MHxzZWFyY2h8MjN8fGNhcnxlbnwwfHwwfHx8MA%3D%3D&auto=format&fit=crop&w=500&q=60"
      }
    ],
    "features": [
      "ABS brakes",
      "Air conditioning",
      "Driver airbag",
      "Passenger airbag",
      "Alloy wheels",
      "CD Stacker",
      "Central locking",
      "Climate control",
      "Cruise Control",
      "Electric Mirrors",
      "Electric Windows",
      "Factory Alloys",
      "Fog lights",
      "Power Steering",
      "Rain sensing wipers",
      "Traction Control",
      "Xenon headlights",
      "Smart key",
      "Reversing Camera",
      "Alarm",
      "VTNZ appraised",
      "DVD",
      "Parking Sensors",
      "Body Kit",
      "Exhaust Brakes",
      "Radio",
      "Remote Locking",
      "Spot Lights",
      "Adaptive Cruise Control",
      "All Electrics",
      "Car Stereo"
    ],
    "status": "Listing",
    "createdAt": "2023-08-15T00:00:00.000Z"
  },
  {
    "title": "Toyota Camry SE",
    "price": 18000,
    "description": "A sleek Toyota Camry with modern features.",
    "stockNo": 654321,
    "vinNo": "PQR123456789",
    "chassisNo": "LMN987654321",
    "numberPlate": "PQR-654",
    "make": "Toyota",
    "model": "Camry",
    "year": 2017,
    "kilometers": 40000,
    "body": "Sedan",
    "transmission": "Automatic",
    "doors": 4,
    "seats": 5,
    "color": "Silver",
    "fuelType": "Petrol",
    "engineSize": "2.5L",
    "wofExpire": "2024-04-15T00:00:00.000Z",
    "regoExpire": "2024-05-01T00:00:00.000Z",
    "numberOfOwners": 2,
    "cylinders": 4,
    "images": [
      {
        "public_id": "toyota-camry-image1",
        "url": "https://images.unsplash.com/photo-1590362891991-f776e747a588?ixlib=rb-4.0.3&ixid=M3wxMjA3fDB8MHxzZWFyY2h8Mjl8fGNhcnxlbnwwfHwwfHx8MA%3D%3D&auto=format&fit=crop&w=500&q=60"
      },
      {
        "public_id": "toyota-camry-image2",
        "url": "https://plus.unsplash.com/premium_photo-1682141683929-e5ac8f0d3be1?ixlib=rb-4.0.3&ixid=M3wxMjA3fDB8MHxzZWFyY2h8MTN8fGNhcnxlbnwwfHwwfHx8MA%3D%3D&auto=format&fit=crop&w=500&q=60"
      }
    ],
    "features": [
      "ABS brakes",
      "Air conditioning",
      "Driver airbag",
      "Passenger airbag",
      "Alloy wheels",
      "CD Stacker",
      "Central locking",
      "Climate control",
      "Cruise Control",
      "Electric Mirrors",
      "Electric Windows",
      "Factory Alloys",
      "Fog lights",
      "Power Steering",
      "Rain sensing wipers",
      "Traction Control",
      "Xenon headlights",
      "Smart key",
      "Reversing Camera",
      "Alarm",
      "VTNZ appraised",
      "DVD",
      "Parking Sensors",
      "Body Kit",
      "Exhaust Brakes",
      "Radio",
      "Remote Locking",
      "Spot Lights",
      "Adaptive Cruise Control",
      "All Electrics",
      "Car Stereo"
    ],
    "status": "Listing",
    "createdAt": "2023-08-20T00:00:00.000Z"
  },
  {
    "title": "Ford Mustang GT",
    "price": 35000,
    "description": "A powerful Ford Mustang with a classic design.",
    "stockNo": 123987,
    "vinNo": "LMN987654321",
    "chassisNo": "ABC123456789",
    "numberPlate": "LMN-123",
    "make": "Ford",
    "model": "Mustang",
    "year": 2020,
    "kilometers": 15000,
    "body": "Coupe",
    "transmission": "Automatic",
    "doors": 2,
    "seats": 4,
    "color": "Red",
    "fuelType": "Petrol",
    "engineSize": "5.0L",
    "wofExpire": "2025-01-15T00:00:00.000Z",
    "regoExpire": "2025-02-01T00:00:00.000Z",
    "numberOfOwners": 1,
    "cylinders": 8,
    "images": [
      {
        "public_id": "ford-mustang-image1",
        "url": "https://images.unsplash.com/photo-1541899481282-d53bffe3c35d?ixlib=rb-4.0.3&ixid=M3wxMjA3fDB8MHxzZWFyY2h8Mjh8fGNhcnxlbnwwfHwwfHx8MA%3D%3D&auto=format&fit=crop&w=500&q=60"
      },
      {
        "public_id": "ford-mustang-image2",
        "url": "https://images.unsplash.com/photo-1471174617910-3e9c04f58ff5?ixlib=rb-4.0.3&ixid=M3wxMjA3fDB8MHxzZWFyY2h8MzN8fGNhcnxlbnwwfHwwfHx8MA%3D%3D&auto=format&fit=crop&w=500&q=60"
      }
    ],
    "features": [
      "ABS brakes",
      "Air conditioning",
      "Driver airbag",
      "Passenger airbag",
      "Alloy wheels",
      "CD Stacker",
      "Central locking",
      "Climate control",
      "Cruise Control",
      "Electric Mirrors",
      "Electric Windows",
      "Factory Alloys",
      "Fog lights",
      "Power Steering",
      "Rain sensing wipers",
      "Traction Control",
      "Xenon headlights",
      "Smart key",
      "Reversing Camera",
      "Alarm",
      "VTNZ appraised",
      "DVD",
      "Parking Sensors",
      "Body Kit",
      "Exhaust Brakes",
      "Radio",
      "Remote Locking",
      "Spot Lights",
      "All Electrics",
      "Car Stereo"
    ],
    "status": "On Hold",
    "createdAt": "2023-08-25T00:00:00.000Z"
  },
  {
    "title": "Nissan Rogue SV",
    "price": 28000,
    "description": "A versatile Nissan Rogue with ample cargo space.",
    "stockNo": 789456,
    "vinNo": "XYZ789654123",
    "chassisNo": "PQR987654321",
    "numberPlate": "XYZ-789",
    "make": "Nissan",
    "model": "Rogue",
    "year": 2018,
    "kilometers": 25000,
    "body": "SUV",
    "transmission": "CVT",
    "doors": 4,
    "seats": 5,
    "color": "Blue",
    "fuelType": "Petrol",
    "engineSize": "2.5L",
    "wofExpire": "2024-06-15T00:00:00.000Z",
    "regoExpire": "2024-07-01T00:00:00.000Z",
    "numberOfOwners": 1,
    "cylinders": 4,
    "images": [
      {
        "public_id": "nissan-rogue-image1",
        "url": "https://images.unsplash.com/photo-1518306727298-4c17e1bf6942?ixlib=rb-4.0.3&ixid=M3wxMjA3fDB8MHxzZWFyY2h8MjZ8fGNhcnxlbnwwfHwwfHx8MA%3D%3D&auto=format&fit=crop&w=500&q=60"
      },
      {
        "public_id": "nissan-rogue-image2",
        "url": "https://images.unsplash.com/photo-1567808291548-fc3ee04dbcf0?ixlib=rb-4.0.3&ixid=M3wxMjA3fDB8MHxzZWFyY2h8MTR8fGNhcnxlbnwwfHwwfHx8MA%3D%3D&auto=format&fit=crop&w=500&q=60"
      }
    ],
    "features": [
      "ABS brakes",
      "Air conditioning",
      "Driver airbag",
      "Passenger airbag",
      "Alloy wheels",
      "CD Stacker",
      "Central locking",
      "Climate control",
      "Cruise Control",
      "Electric Mirrors",
      "Electric Windows",
      "Factory Alloys",
      "Fog lights",
      "Power Steering",
      "Rain sensing wipers",
      "Traction Control",
      "Smart key",
      "Reversing Camera",
      "Alarm",
      "VTNZ appraised",
      "Parking Sensors",
      "Exhaust Brakes",
      "Radio",
      "Remote Locking",
      "Spot Lights",
      "All Electrics",
      "Car Stereo"
    ],
    "status": "Sold",
    "createdAt": "2023-08-30T00:00:00.000Z"
  },
  {
    "title": "Honda Civic EX",
    "price": 20000,
    "description": "A sporty Honda Civic with advanced technology features.",
    "status": "Listing",
    "stockNo": 456789,
    "vinNo": "LMN456789123",
    "chassisNo": "PQR987654321",
    "numberPlate": "LMN-456",
    "make": "Honda",
    "model": "Civic",
    "year": 2020,
    "kilometers": 25000,
    "body": "Sedan",
    "transmission": "CVT",
    "doors": 4,
    "seats": 5,
    "color": "Black",
    "fuelType": "Petrol",
    "engineSize": "2.0L",
    "wofExpire": "2025-01-15",
    "regoExpire": "2025-02-01",
    "numberOfOwners": 1,
    "cylinders": 4,
    "images": [
      {
        "public_id": "honda-civic-image1",
        "url": "https://images.unsplash.com/photo-1485291571150-772bcfc10da5?ixlib=rb-4.0.3&ixid=M3wxMjA3fDB8MHxzZWFyY2h8MjB8fGNhcnxlbnwwfHwwfHx8MA%3D%3D&auto=format&fit=crop&w=500&q=60"
      },
      {
        "public_id": "honda-civic-image2",
        "url": "https://images.unsplash.com/photo-1485291571150-772bcfc10da5?ixlib=rb-4.0.3&ixid=M3wxMjA3fDB8MHxzZWFyY2h8MjB8fGNhcnxlbnwwfHwwfHx8MA%3D%3D&auto=format&fit=crop&w=500&q=60"
      }
    ],
    "features": [
      "ABS brakes",
      "Air conditioning",
      "Driver airbag",
      "Passenger airbag",
      "Electric Mirrors",
      "Electric Windows",
      "CD Stacker",
      "Central locking",
      "Climate control",
      "Power Steering",
      "Rain sensing wipers",
      "Xenon headlights",
      "Smart key",
      "Reversing Camera",
      "Alarm",
      "VTNZ appraised",
      "Parking Sensors",
      "Radio",
      "Remote Locking",
      "Spot Lights",
      "All Electrics",
      "Car Stereo"
    ],
    "createdAt": "2023-08-20"
  },
  {
    "title": "Ford Escape SE",
    "price": 24000,
    "description": "A versatile Ford Escape with spacious interior.",
    "status": "On Hold",
    "stockNo": 789123,
    "vinNo": "XYZ789123456",
    "chassisNo": "PQR654987321",
    "numberPlate": "XYZ-789",
    "make": "Ford",
    "model": "Escape",
    "year": 2018,
    "kilometers": 30000,
    "body": "SUV",
    "transmission": "Automatic",
    "doors": 5,
    "seats": 5,
    "color": "White",
    "fuelType": "Petrol",
    "engineSize": "2.5L",
    "wofExpire": "2024-06-15",
    "regoExpire": "2024-07-01",
    "numberOfOwners": 2,
    "cylinders": 4,
    "images": [
      {
        "public_id": "ford-escape-image1",
        "url": "https://images.unsplash.com/photo-1603584173870-7f23fdae1b7a?ixlib=rb-4.0.3&ixid=M3wxMjA3fDB8MHxzZWFyY2h8Mzl8fGNhcnxlbnwwfHwwfHx8MA%3D%3D&auto=format&fit=crop&w=500&q=60"
      },
      {
        "public_id": "ford-escape-image2",
        "url": "https://images.unsplash.com/photo-1603584173870-7f23fdae1b7a?ixlib=rb-4.0.3&ixid=M3wxMjA3fDB8MHxzZWFyY2h8Mzl8fGNhcnxlbnwwfHwwfHx8MA%3D%3D&auto=format&fit=crop&w=500&q=60"
      }
    ],
    "features": [
      "ABS brakes",
      "Air conditioning",
      "Driver airbag",
      "Passenger airbag",
      "Electric Mirrors",
      "Electric Windows",
      "CD Stacker",
      "Central locking",
      "Climate control",
      "Cruise Control",
      "Power Steering",
      "Rain sensing wipers",
      "Traction Control",
      "Smart key",
      "Reversing Camera",
      "Alarm",
      "VTNZ appraised",
      "Parking Sensors",
      "Radio",
      "Remote Locking",
      "Spot Lights",
      "All Electrics",
      "Car Stereo"
    ],
    "createdAt": "2023-08-25"
  },
  {
    "title": "Ford Escape SE",
    "price": 24000,
    "description": "A versatile Ford Escape with spacious interior.",
    "status": "On Hold",
    "stockNo": 789123,
    "vinNo": "XYZ789123456",
    "chassisNo": "PQR654987321",
    "numberPlate": "XYZ-789",
    "make": "Ford",
    "model": "Escape",
    "year": 2018,
    "kilometers": 30000,
    "body": "SUV",
    "transmission": "Automatic",
    "doors": 5,
    "seats": 5,
    "color": "White",
    "fuelType": "Petrol",
    "engineSize": "2.5L",
    "wofExpire": "2024-06-15",
    "regoExpire": "2024-07-01",
    "numberOfOwners": 2,
    "cylinders": 4,
    "images": [
      {
        "public_id": "ford-escape-image1",
        "url": "https://images.unsplash.com/photo-1549927681-0b673b8243ab?ixlib=rb-4.0.3&ixid=M3wxMjA3fDB8MHxzZWFyY2h8NDB8fGNhcnxlbnwwfHwwfHx8MA%3D%3D&auto=format&fit=crop&w=500&q=60"
      },
      {
        "public_id": "ford-escape-image2",
        "url": "https://images.unsplash.com/photo-1549927681-0b673b8243ab?ixlib=rb-4.0.3&ixid=M3wxMjA3fDB8MHxzZWFyY2h8NDB8fGNhcnxlbnwwfHwwfHx8MA%3D%3D&auto=format&fit=crop&w=500&q=60"
      }
    ],
    "features": [
      "ABS brakes",
      "Air conditioning",
      "Driver airbag",
      "Passenger airbag",
      "Electric Mirrors",
      "Electric Windows",
      "CD Stacker",
      "Central locking",
      "Climate control",
      "Cruise Control",
      "Power Steering",
      "Rain sensing wipers",
      "Traction Control",
      "Smart key",
      "Reversing Camera",
      "Alarm",
      "VTNZ appraised",
      "Parking Sensors",
      "Radio",
      "Remote Locking",
      "Spot Lights",
      "All Electrics",
      "Car Stereo"
    ],
    "createdAt": "2023-08-25"
  },
  {
    "title": "Chevrolet Tahoe LT",
    "price": 35000,
    "description": "A spacious Chevrolet Tahoe with luxury features.",
    "status": "In Transit",
    "stockNo": 987321,
    "vinNo": "ABC987654321",
    "chassisNo": "XYZ123456789",
    "numberPlate": "ABC-987",
    "make": "Chevrolet",
    "model": "Tahoe",
    "year": 2021,
    "kilometers": 15000,
    "body": "SUV",
    "transmission": "Automatic",
    "doors": 4,
    "seats": 7,
    "color": "Gray",
    "fuelType": "Petrol",
    "engineSize": "5.3L",
    "wofExpire": "2026-01-15",
    "regoExpire": "2026-02-01",
    "numberOfOwners": 1,
    "cylinders": 8,
    "images": [
      {
        "public_id": "chevrolet-tahoe-image1",
        "url": "https://images.unsplash.com/photo-1511919884226-fd3cad34687c?ixlib=rb-4.0.3&ixid=M3wxMjA3fDB8MHxzZWFyY2h8MTF8fGNhcnxlbnwwfHwwfHx8MA%3D%3D&auto=format&fit=crop&w=500&q=60"
      },
      {
        "public_id": "chevrolet-tahoe-image2",
        "url": "https://images.unsplash.com/photo-1511919884226-fd3cad34687c?ixlib=rb-4.0.3&ixid=M3wxMjA3fDB8MHxzZWFyY2h8MTF8fGNhcnxlbnwwfHwwfHx8MA%3D%3D&auto=format&fit=crop&w=500&q=60"
      }
    ],
    "features": [
      "ABS brakes",
      "Air conditioning",
      "Driver airbag",
      "Passenger airbag",
      "Alloy wheels",
      "CD Stacker",
      "Central locking",
      "Climate control",
      "Cruise Control",
      "Electric Mirrors",
      "Electric Windows",
      "Factory Alloys",
      "Fog lights",
      "Power Steering",
      "Traction Control",
      "Xenon headlights",
      "Smart key",
      "Reversing Camera",
      "Alarm",
      "VTNZ appraised",
      "Parking Sensors",
      "Exhaust Brakes",
      "Radio",
      "Remote Locking",
      "Spot Lights",
      "All Electrics",
      "Car Stereo"
    ],
    "createdAt": "2023-09-01"
  },
  {
    "title": "BMW X5 xDrive40i",
    "price": 42000,
    "description": "A luxurious BMW X5 with powerful performance.",
    "status": "Sold",
    "stockNo": 654987,
    "vinNo": "PQR987123456",
    "chassisNo": "LMN654321789",
    "numberPlate": "PQR-654",
    "make": "BMW",
    "model": "X5",
    "year": 2022,
    "kilometers": 10000,
    "body": "SUV",
    "transmission": "Automatic",
    "doors": 5,
    "seats": 5,
    "color": "Blue",
    "fuelType": "Petrol",
    "engineSize": "3.0L",
    "wofExpire": "2027-01-15",
    "regoExpire": "2027-02-01",
    "numberOfOwners": 1,
    "cylinders": 6,
    "images": [
      {
        "public_id": "bmw-x5-image1",
        "url": "https://images.unsplash.com/photo-1494976388531-d1058494cdd8?ixlib=rb-4.0.3&ixid=M3wxMjA3fDB8MHxzZWFyY2h8NXx8Y2FyfGVufDB8fDB8fHww&auto=format&fit=crop&w=500&q=60"
      },
      {
        "public_id": "bmw-x5-image2",
        "url": "https://images.unsplash.com/photo-1494976388531-d1058494cdd8?ixlib=rb-4.0.3&ixid=M3wxMjA3fDB8MHxzZWFyY2h8NXx8Y2FyfGVufDB8fDB8fHww&auto=format&fit=crop&w=500&q=60"
      }
    ],
    "features": [
      "ABS brakes",
      "Air conditioning",
      "Driver airbag",
      "Passenger airbag",
      "Alloy wheels",
      "CD Stacker",
      "Central locking",
      "Climate control",
      "Cruise Control",
      "Electric Mirrors",
      "Electric Windows",
      "Factory Alloys",
      "Fog lights",
      "Power Steering",
      "Rain sensing wipers",
      "Traction Control",
      "Xenon headlights",
      "Smart key",
      "Reversing Camera",
      "Alarm",
      "VTNZ appraised",
      "Parking Sensors",
      "Radio",
      "Remote Locking",
      "Spot Lights",
      "All Electrics",
      "Car Stereo"
    ],
    "createdAt": "2023-09-05"
  },
  {
    "title": "Audi Q7 Premium",
    "price": 48000,
    "description": "An elegant Audi Q7 with luxurious interior.",
    "status": "Listing",
    "stockNo": 321456,
    "vinNo": "ABC321456789",
    "chassisNo": "XYZ654987321",
    "numberPlate": "ABC-321",
    "make": "Audi",
    "model": "Q7",
    "year": 2020,
    "kilometers": 20000,
    "body": "SUV",
    "transmission": "Automatic",
    "doors": 5,
    "seats": 7,
    "color": "White",
    "fuelType": "Petrol",
    "engineSize": "3.0L",
    "wofExpire": "2025-03-15",
    "regoExpire": "2025-04-01",
    "numberOfOwners": 1,
    "cylinders": 6,
    "images": [
      {
        "public_id": "audi-q7-image1",
        "url": "https://images.unsplash.com/photo-1502877338535-766e1452684a?ixlib=rb-4.0.3&ixid=M3wxMjA3fDB8MHxzZWFyY2h8NHx8Y2FyfGVufDB8fDB8fHww&auto=format&fit=crop&w=500&q=60"
      },
      {
        "public_id": "audi-q7-image2",
        "url": "https://images.unsplash.com/photo-1502877338535-766e1452684a?ixlib=rb-4.0.3&ixid=M3wxMjA3fDB8MHxzZWFyY2h8NHx8Y2FyfGVufDB8fDB8fHww&auto=format&fit=crop&w=500&q=60"
      }
    ],
    "features": [
      "ABS brakes",
      "Air conditioning",
      "Driver airbag",
      "Passenger airbag",
      "Alloy wheels",
      "CD Stacker",
      "Central locking",
      "Climate control",
      "Cruise Control",
      "Electric Mirrors",
      "Electric Windows",
      "Factory Alloys",
      "Fog lights",
      "Power Steering",
      "Rain sensing wipers",
      "Traction Control",
      "Xenon headlights",
      "Smart key",
      "Reversing Camera",
      "Alarm",
      "VTNZ appraised",
      "Parking Sensors",
      "Radio",
      "Remote Locking",
      "Spot Lights",
      "All Electrics",
      "Car Stereo"
    ],
    "createdAt": "2023-09-10"
  }
  
  
  
  
  
  
]
